polygon_mapper/__init__.py
polygon_mapper/cli.py
polygon_mapper/src.py
polygon_mapper-0.1.1.dist-info/DESCRIPTION.rst
polygon_mapper-0.1.1.dist-info/METADATA
polygon_mapper-0.1.1.dist-info/RECORD
polygon_mapper-0.1.1.dist-info/WHEEL
polygon_mapper-0.1.1.dist-info/entry_points.txt
polygon_mapper-0.1.1.dist-info/metadata.json
polygon_mapper-0.1.1.dist-info/top_level.txt
