Metadata-Version: 2.0
Name: polygon-mapper
Version: 0.1.1
Summary: Opens a webbrowser displaying input polygon on a satellite map
Home-page: https://github.com/medwig/polygon-mapper
Author: Jonathan Medwig
Author-email: jonmedwig@gmail.com
License: MIT
Platform: any
Classifier: Development Status :: 4 - Beta
Classifier: Environment :: Console
Classifier: Intended Audience :: Developers
Classifier: License :: OSI Approved :: BSD License
Classifier: Operating System :: POSIX
Classifier: Operating System :: MacOS
Classifier: Operating System :: Unix
Classifier: Operating System :: Microsoft :: Windows
Classifier: Programming Language :: Python
Classifier: Programming Language :: Python :: 2
Classifier: Programming Language :: Python :: 3
Classifier: Topic :: Software Development :: Libraries :: Python Modules
Requires-Dist: click
